[
  {
    "params": {
      "batchSize": 32,
      "learningRate": 0.001,
      "lstmUnits": [
        64,
        32
      ],
      "dropoutRate": 0.2,
      "l2Regularization": 0.000001
    },
    "score": 0.05246224975333076,
    "evaluation": {
      "mse": 0.027280271079829,
      "mae": 0.13850047107133054,
      "directionalAccuracy": 100,
      "validPredictions": 194,
      "totalPredictions": 194
    },
    "timestamp": "2024-11-15T05:41:48.736Z"
  },
  {
    "params": {
      "batchSize": 32,
      "learningRate": 0.0005,
      "lstmUnits": [
        64,
        32
      ],
      "dropoutRate": 0.3,
      "l2Regularization": 0.00005
    },
    "score": 0.05445061765913397,
    "evaluation": {
      "mse": 0.03089292417411855,
      "mae": 0.1403114932982885,
      "directionalAccuracy": 100,
      "validPredictions": 194,
      "totalPredictions": 194
    },
    "timestamp": "2024-11-15T05:50:09.075Z"
  },
  {
    "params": {
      "batchSize": 32,
      "learningRate": 0.0005,
      "lstmUnits": [
        64,
        32
      ],
      "dropoutRate": 0.3,
      "l2Regularization": 0.0001
    },
    "score": 0.055868549191249985,
    "evaluation": {
      "mse": 0.030890170728319934,
      "mae": 0.14504160299974003,
      "directionalAccuracy": 100,
      "validPredictions": 194,
      "totalPredictions": 194
    },
    "timestamp": "2024-11-15T05:52:32.932Z"
  },
  {
    "params": {
      "batchSize": 32,
      "learningRate": 0.0005,
      "lstmUnits": [
        64,
        32
      ],
      "dropoutRate": 0.3,
      "l2Regularization": 0.0002
    },
    "score": 0.05475694219606887,
    "evaluation": {
      "mse": 0.02934032293248162,
      "mae": 0.14340271007692076,
      "directionalAccuracy": 100,
      "validPredictions": 194,
      "totalPredictions": 194
    },
    "timestamp": "2024-11-15T05:57:40.785Z"
  },
  {
    "params": {
      "batchSize": 32,
      "learningRate": 0.0005,
      "lstmUnits": [
        64,
        32
      ],
      "dropoutRate": 0.4,
      "l2Regularization": 0.00005
    },
    "score": 0.05861163588261737,
    "evaluation": {
      "mse": 0.03384491120440777,
      "mae": 0.15024557133618088,
      "directionalAccuracy": 100,
      "validPredictions": 194,
      "totalPredictions": 194
    },
    "timestamp": "2024-11-15T06:00:58.008Z"
  },
  {
    "params": {
      "batchSize": 32,
      "learningRate": 0.0005,
      "lstmUnits": [
        64,
        32
      ],
      "dropoutRate": 0.4,
      "l2Regularization": 0.0001
    },
    "score": 0.052646033031104,
    "evaluation": {
      "mse": 0.027592793647551284,
      "mae": 0.1386963852402783,
      "directionalAccuracy": 100,
      "validPredictions": 194,
      "totalPredictions": 194
    },
    "timestamp": "2024-11-15T06:06:31.586Z"
  },
  {
    "params": {
      "batchSize": 32,
      "learningRate": 0.0005,
      "lstmUnits": [
        64,
        32
      ],
      "dropoutRate": 0.4,
      "l2Regularization": 0.0002
    },
    "score": 0.05340641922628115,
    "evaluation": {
      "mse": 0.028189547099594855,
      "mae": 0.14043533462147736,
      "directionalAccuracy": 100,
      "validPredictions": 194,
      "totalPredictions": 194
    },
    "timestamp": "2024-11-15T06:09:04.264Z"
  },
  {
    "params": {
      "batchSize": 32,
      "learningRate": 0.0005,
      "lstmUnits": [
        64,
        32
      ],
      "dropoutRate": 0.5,
      "l2Regularization": 0.00005
    },
    "score": 0.05296127415657742,
    "evaluation": {
      "mse": 0.027511558185389317,
      "mae": 0.13985550294140564,
      "directionalAccuracy": 100,
      "validPredictions": 194,
      "totalPredictions": 194
    },
    "timestamp": "2024-11-15T06:11:32.162Z"
  },
  {
    "params": {
      "batchSize": 32,
      "learningRate": 0.0005,
      "lstmUnits": [
        64,
        32
      ],
      "dropoutRate": 0.5,
      "l2Regularization": 0.0001
    },
    "score": 0.05276493012775617,
    "evaluation": {
      "mse": 0.02814751002018517,
      "mae": 0.138353087065607,
      "directionalAccuracy": 100,
      "validPredictions": 194,
      "totalPredictions": 194
    },
    "timestamp": "2024-11-15T06:16:19.559Z"
  },
  {
    "params": {
      "batchSize": 32,
      "learningRate": 0.0005,
      "lstmUnits": [
        64,
        32
      ],
      "dropoutRate": 0.5,
      "l2Regularization": 0.0002
    },
    "score": 0.052411060042850705,
    "evaluation": {
      "mse": 0.02776073679294005,
      "mae": 0.13768921775224896,
      "directionalAccuracy": 100,
      "validPredictions": 194,
      "totalPredictions": 194
    },
    "timestamp": "2024-11-15T06:19:29.560Z"
  },
  {
    "params": {
      "batchSize": 32,
      "learningRate": 0.0005,
      "lstmUnits": [
        96,
        48
      ],
      "dropoutRate": 0.3,
      "l2Regularization": 0.00005
    },
    "score": 0.05157945317250238,
    "evaluation": {
      "mse": 0.026334929223465992,
      "mae": 0.1368182716103866,
      "directionalAccuracy": 100,
      "validPredictions": 194,
      "totalPredictions": 194
    },
    "timestamp": "2024-11-15T06:22:27.540Z"
  },
  {
    "params": {
      "batchSize": 32,
      "learningRate": 0.0005,
      "lstmUnits": [
        96,
        48
      ],
      "dropoutRate": 0.3,
      "l2Regularization": 0.0001
    },
    "score": 0.05230753154300921,
    "evaluation": {
      "mse": 0.027267491512371175,
      "mae": 0.13800178312686914,
      "directionalAccuracy": 100,
      "validPredictions": 194,
      "totalPredictions": 194
    },
    "timestamp": "2024-11-15T06:25:00.039Z"
  },
  {
    "params": {
      "batchSize": 32,
      "learningRate": 0.0005,
      "lstmUnits": [
        96,
        48
      ],
      "dropoutRate": 0.3,
      "l2Regularization": 0.0002
    },
    "score": 0.05235293845538099,
    "evaluation": {
      "mse": 0.02721880174226433,
      "mae": 0.13821805919491753,
      "directionalAccuracy": 100,
      "validPredictions": 194,
      "totalPredictions": 194
    },
    "timestamp": "2024-11-15T06:28:04.198Z"
  },
  {
    "params": {
      "batchSize": 32,
      "learningRate": 0.0005,
      "lstmUnits": [
        96,
        48
      ],
      "dropoutRate": 0.4,
      "l2Regularization": 0.00005
    },
    "score": 0.053503756365199565,
    "evaluation": {
      "mse": 0.028490157183231793,
      "mae": 0.14035897830635616,
      "directionalAccuracy": 100,
      "validPredictions": 194,
      "totalPredictions": 194
    },
    "timestamp": "2024-11-15T06:33:44.853Z"
  }
]