[
  {
    "timestamp": 1731513411566,
    "predictedChange": 0.3087918758392334,
    "predictedPrice": 216.42624935131073,
    "confidence": 74.5015303884148,
    "metadata": {
      "price": {
        "open": 214.81,
        "high": 216,
        "low": 214.6,
        "close": 215.76
      },
      "indicators": {
        "rsi": 65.0933986165482,
        "momentum": 3.6261466788338526,
        "macd": 0.4954564162364701,
        "roc": 4.1664655047554655,
        "bBands": {
          "bandwidth": 0.06919501889679054,
          "percentB": 82.55688400054406,
          "deviation": 1.3022753600217618
        }
      },
      "analysis": {
        "trend": "uptrend",
        "strength": "strong",
        "volatility": 0.006517387458684445,
        "riskLevel": 0.15260695498347376
      }
    }
  }
]